rstr/__init__.py
rstr/py.typed
rstr/rstr_base.py
rstr/xeger.py
rstr/tests/__init__.py
rstr/tests/test_package_level_access.py
rstr/tests/test_rstr.py
rstr/tests/test_xeger.py
rstr-3.2.0.dist-info/LICENSE.txt
rstr-3.2.0.dist-info/METADATA
rstr-3.2.0.dist-info/WHEEL
rstr-3.2.0.dist-info/top_level.txt
rstr-3.2.0.dist-info/RECORD
