Metadata-Version: 2.1
Name: rstr
Version: 3.2.0
Summary: Generate random strings in Python
Home-page: https://github.com/leapfrogonline/rstr
Author: Leapfrog Direct Response LLC
Author-email: oss@leapfrogdevelopment.com
Maintainer: Brendan McCollam
Maintainer-email: rstr@mccoll.am
License: UNKNOWN
Keywords: random string,reverse regex,reverse regular expression,testing,fuzz testing
Platform: UNKNOWN
Classifier: Development Status :: 5 - Production/Stable
Classifier: Intended Audience :: Developers
Classifier: License :: OSI Approved :: BSD License
Classifier: Operating System :: OS Independent
Classifier: Programming Language :: Python :: 3.7
Classifier: Programming Language :: Python :: 3.8
Classifier: Programming Language :: Python :: 3.9
Classifier: Programming Language :: Python :: 3.10
Classifier: Topic :: Software Development :: Testing
Requires-Python: >=3.7
